README.md
setup.py
thean_tools/__init__.py
thean_tools/decorator.py
thean_tools/file.py
thean_tools/image.py
thean_tools/ocr.py
thean_tools.egg-info/PKG-INFO
thean_tools.egg-info/SOURCES.txt
thean_tools.egg-info/dependency_links.txt
thean_tools.egg-info/requires.txt
thean_tools.egg-info/top_level.txt