Metadata-Version: 2.1
Name: thean-tools
Version: 0.0.14
Summary: some tools for ocr
Home-page: https://github.com/ValidSolution/lib-tools
Author: Thean
Author-email: ah_tomorrow@163.com
License: UNKNOWN
Platform: UNKNOWN
Requires-Python: >=3.5
